financial_datasets/__init__.py
financial_datasets/dataset.py
financial_datasets/filings.py
financial_datasets/generator.py
financial_datasets/llm/__init__.py
financial_datasets/llm/openai.py
financial_datasets/parser.py
financial_datasets/prompts.py
financial_datasets/tools.py
financial_datasets-0.1.18.dist-info/LICENSE
financial_datasets-0.1.18.dist-info/METADATA
financial_datasets-0.1.18.dist-info/WHEEL
financial_datasets-0.1.18.dist-info/RECORD
