Metadata-Version: 2.1
Name: financial-datasets
Version: 0.1.18
Summary: Financial datasets for LLMs
License: MIT
Author: Virat Singh
Author-email: virat@virat.ai
Requires-Python: >=3.10,<4.0
Classifier: License :: OSI Approved :: MIT License
Classifier: Programming Language :: Python :: 3
Classifier: Programming Language :: Python :: 3.10
Classifier: Programming Language :: Python :: 3.11
Requires-Dist: edgartools (==2.21.1)
Requires-Dist: langchain-text-splitters (>=0.0.1,<0.0.2)
Requires-Dist: openai (>=1.28.1,<2.0.0)
Requires-Dist: pydantic (==2.7.1)
Requires-Dist: pypdf2 (>=3.0.1,<4.0.0)
Requires-Dist: python-dotenv (>=1.0.1,<2.0.0)
Requires-Dist: tiktoken (>=0.6.0,<0.7.0)
